kiara_plugin/language_processing/__init__.py
kiara_plugin/language_processing/data_types.py
kiara_plugin/language_processing/defaults.py
kiara_plugin/language_processing/models.py
kiara_plugin/language_processing/py.typed
kiara_plugin/language_processing/version.txt
kiara_plugin/language_processing/modules/__init__.py
kiara_plugin/language_processing/modules/lda.py
kiara_plugin/language_processing/modules/lemmatize.py
kiara_plugin/language_processing/modules/tokens.py
kiara_plugin/language_processing/pipelines/.gitkeep
kiara_plugin/language_processing/pipelines/__init__.py
kiara_plugin/language_processing/resources/.gitkeep
kiara_plugin.language_processing-0.5.0.dist-info/AUTHORS.md
kiara_plugin.language_processing-0.5.0.dist-info/LICENSE
kiara_plugin.language_processing-0.5.0.dist-info/METADATA
kiara_plugin.language_processing-0.5.0.dist-info/WHEEL
kiara_plugin.language_processing-0.5.0.dist-info/entry_points.txt
kiara_plugin.language_processing-0.5.0.dist-info/top_level.txt
kiara_plugin.language_processing-0.5.0.dist-info/RECORD
