Metadata-Version: 2.1
Name: kiara-plugin.language-processing
Version: 0.5.0
Summary: Language-processing kiara modules and data types.
Author-email: Markus Binsteiner <markus@frkl.io>
License: MPL-2.0
Project-URL: homepage, https://github.com/DHARPA-Project/kiara_plugin.language_processing
Project-URL: documentation, https://DHARPA-Project.github.io/kiara_plugin.language_processing
Project-URL: repository, https://github.com/DHARPA-Project/kiara_plugin.language_processing
Keywords: kiara
Classifier: Programming Language :: Python :: 3
Classifier: Development Status :: 3 - Alpha
Classifier: License :: OSI Approved :: Mozilla Public License 2.0 (MPL 2.0)
Classifier: Programming Language :: Python
Classifier: Programming Language :: Python :: 3
Classifier: Programming Language :: Python :: 3 :: Only
Classifier: Programming Language :: Python :: 3.8
Classifier: Programming Language :: Python :: 3.9
Classifier: Programming Language :: Python :: 3.10
Classifier: Programming Language :: Python :: 3.11
Classifier: Programming Language :: Python :: 3.12
Requires-Python: >=3.8
License-File: LICENSE
License-File: AUTHORS.md
Requires-Dist: kiara <0.6.0,>=0.5.3
Requires-Dist: kiara-plugin.core-types <0.6.0,>=0.5.0
Requires-Dist: kiara-plugin.tabular <0.6.0,>=0.5.0
Requires-Dist: gensim >=4.3.0
Requires-Dist: nltk >=3.8
Provides-Extra: dev_all
Requires-Dist: kiara[dev_all] ; extra == 'dev_all'
Provides-Extra: dev_documentation
Requires-Dist: kiara[dev_documentation] ; extra == 'dev_documentation'
Provides-Extra: dev_testing
Requires-Dist: kiara[dev_testing] ; extra == 'dev_testing'
Provides-Extra: dev_utils
Requires-Dist: kiara[dev_utils] ; extra == 'dev_utils'
Provides-Extra: streamlit
Requires-Dist: kiara-plugin.streamlit ; extra == 'streamlit'
